gogo_gemini/__init__.py
gogo_gemini/gogo.py
gogo_gemini-0.1.dist-info/METADATA
gogo_gemini-0.1.dist-info/WHEEL
gogo_gemini-0.1.dist-info/top_level.txt
gogo_gemini-0.1.dist-info/RECORD
